vspell/__init__.py
vspell/__main__.py
vspell/cli.py
vspell/constants.py
vspell/utils/__init__.py
vspell/utils/history.py
vspell/utils/spinner.py
vspell-0.1.4.dist-info/licenses/LICENSE
vspell-0.1.4.dist-info/METADATA
vspell-0.1.4.dist-info/WHEEL
vspell-0.1.4.dist-info/entry_points.txt
vspell-0.1.4.dist-info/top_level.txt
vspell-0.1.4.dist-info/RECORD
