Metadata-Version: 2.4
Name: vspell
Version: 0.1.4
Summary: A simple, command-line voice spelling and transcription tool.
Author-email: Dan Higgins <daniel.higgins@gatech.edu>
License: MIT
Project-URL: Homepage, https://github.com/DanHUMassMed/vspell.git
Requires-Python: >=3.13
License-File: LICENSE
Requires-Dist: build>=1.3.0
Requires-Dist: faster-whisper>=1.2.1
Requires-Dist: pyperclip>=1.11.0
Requires-Dist: scipy>=1.16.3
Requires-Dist: sounddevice>=0.5.3
Requires-Dist: twine>=6.2.0
Dynamic: license-file
